open_meteo_data_dvl/__init__.py
open_meteo_data_dvl/const.py
open_meteo_data_dvl/open_meteo_client.py
open_meteo_data_dvl/open_meteo_sensor.py
open_meteo_data_dvl/open_meteo_station.py
open_meteo_data_dvl/reqiurements.txt
open_meteo_data_dvl-0.2.1.dist-info/METADATA
open_meteo_data_dvl-0.2.1.dist-info/WHEEL
open_meteo_data_dvl-0.2.1.dist-info/licenses/LICENSE
open_meteo_data_dvl-0.2.1.dist-info/RECORD
