Metadata-Version: 2.4
Name: open_meteo_data_dvl
Version: 0.2.1
Summary: Python API client for the open meteo data V1 service, provided by Provincia autonoma di Bolzano - Informatica Alto Adige SPA.
Project-URL: Homepage, https://github.com/dvdvnl/open_meteo_data
Project-URL: Issues, https://github.com/dvdvnl/open_meteo_data/issues
Author-email: david vnl <io@davole.com>
License-File: LICENSE
Classifier: License :: OSI Approved :: MIT License
Classifier: Operating System :: OS Independent
Classifier: Programming Language :: Python :: 3
Requires-Python: >=3.8
